wibblywobbly/__init__.py
wibblywobbly/core.py
wibblywobbly/hierarchical.py
wibblywobbly-0.3.dist-info/LICENSE
wibblywobbly-0.3.dist-info/METADATA
wibblywobbly-0.3.dist-info/WHEEL
wibblywobbly-0.3.dist-info/top_level.txt
wibblywobbly-0.3.dist-info/RECORD
