Metadata-Version: 2.1
Name: wibblywobbly
Version: 0.3
Summary: Python library to create equivalence dictionaries between a set of texts and a catalog using Levenshtein distance.
Home-page: https://github.com/mar-esther23/WibblyWobbly/
Author: ME Martinez-Sanchez
Author-email: mar.esther23+wibblywobbly@gmail.com
License: UNKNOWN
Project-URL: Bug Tracker, https://github.com/mar-esther23/WibblyWobbly/issues
Platform: UNKNOWN
Classifier: Programming Language :: Python :: 3
Classifier: License :: OSI Approved :: MIT License
Classifier: Operating System :: OS Independent
Requires-Python: >=3.6
License-File: LICENSE
